pypi_publish_amash/__init__.py
pypi_publish_amash-0.1.dist-info/WHEEL
pypi_publish_amash-0.1.dist-info/METADATA
pypi_publish_amash-0.1.dist-info/RECORD
